{
  "version": "v2025.07.19-e9abff4",
  "buildDate": "2025-07-19T16:23:20.874Z",
  "displayDate": "Jul 19, 2025, 04:23 PM UTC",
  "environment": "production",
  "git": {
    "hash": "e9abff4",
    "branch": "main",
    "lastCommitDate": "2025-07-19 21:50:20 +0530"
  },
  "github": {
    "runId": "16390533499",
    "repository": "abstractalgorithms/abstractalgorithms.dev",
    "workflow": "Deploy to Production (GitHub Pages)",
    "actor": "abstractalgorithms",
    "eventName": "push",
    "ref": "refs/heads/main"
  },
  "nodeVersion": "v18.20.8",
  "buildId": "1752942200898"
}